<?xml version="1.0"?>
<opencv_storage>
<stage1>
  <maxWeakCount>7</maxWeakCount>
  <stageThreshold>-1.6999421119689941e+00</stageThreshold>
  <weakClassifiers>
    <_>
      <internalNodes>
        0 -1 585 -1024463633 2120081871 -1576777993 1083955887
        1145373055 1400109711 1351575807 -142606337</internalNodes>
      <leafValues>
        -5.7662248611450195e-01 3.3884298801422119e-01</leafValues></_>
    <_>
      <internalNodes>
        0 -1 3006 1636777986 303783951 1356035015 1087893375 1372546043
        1368898031 1911025407 -134217761</internalNodes>
      <leafValues>
        -5.4292953014373779e-01 3.8417628407478333e-01</leafValues></_>
    <_>
      <internalNodes>
        0 -1 6003 -287314166 -2098466165 -364149118 -387581473
        -241437117 71740961 -140791086 -218105893</internalNodes>
      <leafValues>
        -5.0024342536926270e-01 3.7834745645523071e-01</leafValues></_>
    <_>
      <internalNodes>
        0 -1 2106 -295719418 684716943 -435662330 -1293428521 1930128966
        88241698 -6623194 -201852997</internalNodes>
      <leafValues>
        -5.0821965932846069e-01 3.3615809679031372e-01</leafValues></_>
    <_>
      <internalNodes>
        0 -1 2522 -488376704 -761142270 -531575544 -211317621 -219692434
        1884548870 1156030779 -16789649</internalNodes>
      <leafValues>
        -4.4819599390029907e-01 3.8838830590248108e-01</leafValues></_>
    <_>
      <internalNodes>
        0 -1 3377 -637543248 135847936 1363396704 -593503501 -725030728
        1086439435 -913681855 -588252425</internalNodes>
      <leafValues>
        -5.4386544227600098e-01 2.9456123709678650e-01</leafValues></_>
    <_>
      <internalNodes>
        0 -1 6483 -473445625 48095535 872892554 -1499274488 -13796334
        1540012171 -87178433 -880807937</internalNodes>
      <leafValues>
        -3.8556224107742310e-01 4.1350945830345154e-01</leafValues></_></weakClassifiers></stage1>
</opencv_storage>
