<?xml version="1.0"?>
<opencv_storage>
<stage16>
  <maxWeakCount>6</maxWeakCount>
  <stageThreshold>-1.0022457838058472e+00</stageThreshold>
  <weakClassifiers>
    <_>
      <internalNodes>
        0 -1 941 -1324959361 1368613328 1091809597 -796753099 -887475591
        -1691884531 -1615668524 -85263928</internalNodes>
      <leafValues>
        -6.4478766918182373e-01 8.9005239307880402e-02</leafValues></_>
    <_>
      <internalNodes>
        0 -1 901 804726533 583939935 -854134498 819630271 650004327
        1106089923 -1014533033 -356926116</internalNodes>
      <leafValues>
        -6.3097715377807617e-01 2.5907200574874878e-01</leafValues></_>
    <_>
      <internalNodes>
        0 -1 1330 2013089545 983400847 275158431 708829077 -1567395196
        1572992429 710342376 -2001799513</internalNodes>
      <leafValues>
        -5.3953105211257935e-01 3.1659063696861267e-01</leafValues></_>
    <_>
      <internalNodes>
        0 -1 495 183413611 -2130313600 1145803025 -103975406 461977202
        446734232 826352689 -32063101</internalNodes>
      <leafValues>
        -5.2176469564437866e-01 3.6780366301536560e-01</leafValues></_>
    <_>
      <internalNodes>
        0 -1 205 1809706559 -1373765560 536920479 -866861028 27878258
        -11931648 72963273 1768211104</internalNodes>
      <leafValues>
        -5.8888918161392212e-01 3.2645335793495178e-01</leafValues></_>
    <_>
      <internalNodes>
        0 -1 1177 -1616958686 1264714571 1209532576 1195528395
        1756738595 -779581144 -2138121421 2091383231</internalNodes>
      <leafValues>
        -6.0480761528015137e-01 3.0034276843070984e-01</leafValues></_></weakClassifiers></stage16>
</opencv_storage>
