<?xml version="1.0"?>
<opencv_storage>
<stage14>
  <maxWeakCount>8</maxWeakCount>
  <stageThreshold>-8.5326290130615234e-01</stageThreshold>
  <weakClassifiers>
    <_>
      <internalNodes>
        0 -1 816 -741174273 -684092537 117592539 -539717411 -1425884997
        -624263149 -251146851 -547357220</internalNodes>
      <leafValues>
        -5.3426676988601685e-01 2.8216704726219177e-01</leafValues></_>
    <_>
      <internalNodes>
        0 -1 1372 -204488749 1213534605 151607809 446941995 1783345664
        -1375410046 -1045497600 -1740656661</internalNodes>
      <leafValues>
        -4.3016234040260315e-01 3.6819085478782654e-01</leafValues></_>
    <_>
      <internalNodes>
        0 -1 327 -714409046 142664002 -779763006 2009541783 -1852910801
        -1833917992 -115221649 1936923167</internalNodes>
      <leafValues>
        -5.4337817430496216e-01 3.1299963593482971e-01</leafValues></_>
    <_>
      <internalNodes>
        0 -1 131 1727320118 677761307 4363476 -227022213 -1727244268
        -1286731503 1786901368 -350228737</internalNodes>
      <leafValues>
        -5.8912432193756104e-01 2.6908296346664429e-01</leafValues></_>
    <_>
      <internalNodes>
        0 -1 690 -1697820672 -1297039103 51118596 -1056597219 -120848171
        -1182744575 -1541957245 -416177917</internalNodes>
      <leafValues>
        -5.4954934120178223e-01 3.0542060732841492e-01</leafValues></_>
    <_>
      <internalNodes>
        0 -1 1253 -682362926 725810460 -1879010926 1585545433 -390053760
        696778897 -497016126 451617583</internalNodes>
      <leafValues>
        -4.9541848897933960e-01 3.2747843861579895e-01</leafValues></_>
    <_>
      <internalNodes>
        0 -1 208 677883054 -581238653 1183969464 1787503316 1360092006
        2076287232 1095191323 1542311819</internalNodes>
      <leafValues>
        -6.3060379028320312e-01 2.6815354824066162e-01</leafValues></_>
    <_>
      <internalNodes>
        0 -1 1174 2092603576 1394327552 70418 -1508137589 536914335
        -1064795648 -1172902981 -877266847</internalNodes>
      <leafValues>
        -4.1518700122833252e-01 4.2724609375000000e-01</leafValues></_></weakClassifiers></stage14>
</opencv_storage>
