<?xml version="1.0"?>
<opencv_storage>
<stage37>
  <maxWeakCount>7</maxWeakCount>
  <stageThreshold>-3.2159027457237244e-01</stageThreshold>
  <weakClassifiers>
    <_>
      <internalNodes>
        0 -1 6080 687865936 889716736 2162721 320340000 1090519056
        -1853357952 151011497 981467197</internalNodes>
      <leafValues>
        -6.0493826866149902e-01 5.1668894290924072e-01</leafValues></_>
    <_>
      <internalNodes>
        0 -1 6668 222380373 200723 -2113830784 -1605074680 537998782
        -1744830400 285479043 -2113223799</internalNodes>
      <leafValues>
        -5.5713176727294922e-01 4.2443749308586121e-01</leafValues></_>
    <_>
      <internalNodes>
        0 -1 4522 -684482366 926121712 523689969 -1079836747 215878892
        -1648369665 -562161422 -566231175</internalNodes>
      <leafValues>
        -4.5423567295074463e-01 5.5428165197372437e-01</leafValues></_>
    <_>
      <internalNodes>
        0 -1 8394 -297926869 2092662783 -268435457 -1360003585
        -1090560188 2013233149 -830480449 -287711265</internalNodes>
      <leafValues>
        -3.9870598912239075e-01 6.7788076400756836e-01</leafValues></_>
    <_>
      <internalNodes>
        0 -1 5650 1343242426 -141524983 1073758549 1444413652
        -1256146782 279609474 1074305740 1779189903</internalNodes>
      <leafValues>
        -4.9000608921051025e-01 5.5892235040664673e-01</leafValues></_>
    <_>
      <internalNodes>
        0 -1 6383 -114049806 522926714 -1108968527 2033298743
        -1091144475 -1073741825 335435679 -763970019</internalNodes>
      <leafValues>
        -3.7215843796730042e-01 7.0728558301925659e-01</leafValues></_>
    <_>
      <internalNodes>
        0 -1 752 -1436110440 -1455407104 104923393 -712769519 33562635
        -1199538040 -2004842329 -668880719</internalNodes>
      <leafValues>
        -5.4472476243972778e-01 5.2508825063705444e-01</leafValues></_></weakClassifiers></stage37>
</opencv_storage>
